azure/mgmt/hdinsightcontainers/__init__.py
azure/mgmt/hdinsightcontainers/_configuration.py
azure/mgmt/hdinsightcontainers/_hd_insight_containers_mgmt_client.py
azure/mgmt/hdinsightcontainers/_patch.py
azure/mgmt/hdinsightcontainers/_serialization.py
azure/mgmt/hdinsightcontainers/_version.py
azure/mgmt/hdinsightcontainers/py.typed
azure/mgmt/hdinsightcontainers/aio/__init__.py
azure/mgmt/hdinsightcontainers/aio/_configuration.py
azure/mgmt/hdinsightcontainers/aio/_hd_insight_containers_mgmt_client.py
azure/mgmt/hdinsightcontainers/aio/_patch.py
azure/mgmt/hdinsightcontainers/aio/operations/__init__.py
azure/mgmt/hdinsightcontainers/aio/operations/_available_cluster_pool_versions_operations.py
azure/mgmt/hdinsightcontainers/aio/operations/_available_cluster_versions_operations.py
azure/mgmt/hdinsightcontainers/aio/operations/_cluster_available_upgrades_operations.py
azure/mgmt/hdinsightcontainers/aio/operations/_cluster_jobs_operations.py
azure/mgmt/hdinsightcontainers/aio/operations/_cluster_libraries_operations.py
azure/mgmt/hdinsightcontainers/aio/operations/_cluster_pool_available_upgrades_operations.py
azure/mgmt/hdinsightcontainers/aio/operations/_cluster_pool_upgrade_histories_operations.py
azure/mgmt/hdinsightcontainers/aio/operations/_cluster_pools_operations.py
azure/mgmt/hdinsightcontainers/aio/operations/_cluster_upgrade_histories_operations.py
azure/mgmt/hdinsightcontainers/aio/operations/_clusters_operations.py
azure/mgmt/hdinsightcontainers/aio/operations/_locations_operations.py
azure/mgmt/hdinsightcontainers/aio/operations/_operations.py
azure/mgmt/hdinsightcontainers/aio/operations/_patch.py
azure/mgmt/hdinsightcontainers/models/__init__.py
azure/mgmt/hdinsightcontainers/models/_hd_insight_containers_mgmt_client_enums.py
azure/mgmt/hdinsightcontainers/models/_models_py3.py
azure/mgmt/hdinsightcontainers/models/_patch.py
azure/mgmt/hdinsightcontainers/operations/__init__.py
azure_mgmt_hdinsightcontainers-1.0.0b4.dist-info/licenses/LICENSE
azure_mgmt_hdinsightcontainers-1.0.0b4.dist-info/METADATA
azure_mgmt_hdinsightcontainers-1.0.0b4.dist-info/WHEEL
azure_mgmt_hdinsightcontainers-1.0.0b4.dist-info/top_level.txt
azure_mgmt_hdinsightcontainers-1.0.0b4.dist-info/RECORD
